{"sections":{"list_cat_heading":{"type":"list_cat_heading","settings":{"shown":true,"parallax":false,"color":"#ffffff","color_txt":"#1a1a1a","overlay":54,"padding":50,"paddingmb":50,"bg_pos":"center center","bg_repeat":"no-repeat","bg_size":"cover","bg_att":"scroll"}},"main":{"type":"list-collections-template","settings":{"layout":"wide","hoverz":true,"cat_design":"5","cat_space":"30","display_type":"all","sort":"alphabetical","col":"4","col_md":"3","col_mb":"6","pr_txt":"products","use_eq_height":true,"image_ratio":"ratio_nt"}}},"order":["list_cat_heading","main"]}